vDirect/API_requests.py
vDirect/__init__.py
vDirect/main.py
vDirect-0.0.7.dist-info/LICENSE.txt
vDirect-0.0.7.dist-info/METADATA
vDirect-0.0.7.dist-info/WHEEL
vDirect-0.0.7.dist-info/entry_points.txt
vDirect-0.0.7.dist-info/top_level.txt
vDirect-0.0.7.dist-info/RECORD
