Metadata-Version: 2.1
Name: vDirect
Version: 0.0.7
Summary: Command line interface to send requests to the VOGDB-API
Home-page: https://github.com/sigi-k/vDirect
Author: Sigrid Koizar, Nikola Vinko
Author-email: a11741823@unet.univie.ac.at
Maintainer: Sigrid Koizar
Maintainer-email: a11741823@unet.univie.ac.at
License: MIT
Project-URL: Code, https://github.com/sigi-k/vDirect
Platform: UNKNOWN
Classifier: Intended Audience :: End Users/Desktop
Classifier: License :: OSI Approved :: MIT License
Classifier: Operating System :: Unix
Classifier: Programming Language :: Python
Requires-Python: >=3.7
Requires-Dist: requests
Requires-Dist: argparse
